morphcloud/__init__.py
morphcloud/_asyncify.py
morphcloud/_bash_interpreter.py
morphcloud/_llm.py
morphcloud/_scramble.py
morphcloud/_ssh.py
morphcloud/_utils.py
morphcloud/api.py
morphcloud/cli.py
morphcloud/py.typed
morphcloud/experimental/__init__.py
morphcloud/experimental/browser.py
morphcloud-0.1.104.dist-info/METADATA
morphcloud-0.1.104.dist-info/WHEEL
morphcloud-0.1.104.dist-info/entry_points.txt
morphcloud-0.1.104.dist-info/licenses/LICENSE
morphcloud-0.1.104.dist-info/RECORD
