Metadata-Version: 2.4
Name: morphcloud
Version: 0.1.104
Summary: A Python SDK and CLI tool for creating, managing, and interacting with Morph Cloud VMs.
Author-email: Morph Labs <jobs@morph.so>
License: Apache-2.0
License-File: LICENSE
Keywords: cli,cloud,morph,runtimes
Classifier: License :: OSI Approved :: Apache Software License
Classifier: Operating System :: OS Independent
Classifier: Programming Language :: Python :: 3
Requires-Python: >=3.10
Requires-Dist: anthropic>=0.40.0
Requires-Dist: click>=8.1.7
Requires-Dist: httpx>=0.27.0
Requires-Dist: packaging>=24.2
Requires-Dist: paramiko>=3.5.0
Requires-Dist: pathspec>=0.12.1
Requires-Dist: psutil>=6.1.0
Requires-Dist: pydantic>=2.10.3
Requires-Dist: pyyaml>=6.0.2
Requires-Dist: requests>=2.32.3
Requires-Dist: rich>=13.9.4
Requires-Dist: toml>=0.10.2
Requires-Dist: tqdm>=4.67.1
Requires-Dist: websocket-client>=1.8.0
Provides-Extra: dev
Requires-Dist: ruff>=0.11.4; extra == 'dev'
